README.md
setup.py
timeouter/__init__.py
timeouter/core.py
timeouter.egg-info/PKG-INFO
timeouter.egg-info/SOURCES.txt
timeouter.egg-info/dependency_links.txt
timeouter.egg-info/top_level.txt