Metadata-Version: 2.1
Name: timeouter
Version: 0.0.11
Summary: Timeouts helper
Home-page: https://github.com/alttch/timeouter
Author: Altertech
Author-email: div@altertech.com
License: MIT
Platform: UNKNOWN
Classifier: Programming Language :: Python :: 3
Classifier: License :: OSI Approved :: MIT License
Classifier: Topic :: Software Development :: Libraries
